XhscreatorDataCollection/__init__.py
XhscreatorDataCollection/_login_utils.py
XhscreatorDataCollection/collector.py
XhscreatorDataCollection/py.typed
XhscreatorDataCollection/home/home.py
XhscreatorDataCollection/note_manager/_dict.py
XhscreatorDataCollection/note_manager/note_manager.py
XhscreatorDataCollection/statistics/_dict.py
XhscreatorDataCollection/statistics/statistics.py
xhscreator_data_collection-1.0.4.dist-info/METADATA
xhscreator_data_collection-1.0.4.dist-info/WHEEL
xhscreator_data_collection-1.0.4.dist-info/RECORD
