Metadata-Version: 2.4
Name: xhscreator-data-collection
Version: 1.0.4
Summary: XHS Creator Data Collection
Author: martianbugs
Requires-Python: >=3.12
Requires-Dist: browser-automation-launcher>=1.0.7
